kolo-2.40.1.dist-info/METADATA
kolo-2.40.1.dist-info/WHEEL
kolo-2.40.1.dist-info/entry_points.txt
kolo/__init__.py
kolo/__main__.py
kolo/_kolo.cpython-311-darwin.so
kolo/checks.py
kolo/cli_mcp_shared.py
kolo/config.py
kolo/db.py
kolo/django_schema.py
kolo/filters/__init__.py
kolo/filters/attrs.py
kolo/filters/celery.py
kolo/filters/core.py
kolo/filters/django.py
kolo/filters/exception.py
kolo/filters/httpx.py
kolo/filters/huey.py
kolo/filters/kolo.py
kolo/filters/logging.py
kolo/filters/pypy.py
kolo/filters/pytest.py
kolo/filters/requests.py
kolo/filters/sql.py
kolo/filters/unittest.py
kolo/filters/urllib.py
kolo/filters/urllib3.py
kolo/generate_tests/README.md
kolo/generate_tests/__init__.py
kolo/generate_tests/factories.py
kolo/generate_tests/format.py
kolo/generate_tests/loaders.py
kolo/generate_tests/outbound.py
kolo/generate_tests/plan.py
kolo/generate_tests/processors.py
kolo/generate_tests/queries.py
kolo/generate_tests/request.py
kolo/generate_tests/sort.py
kolo/generate_tests/steps.py
kolo/git.py
kolo/kv.py
kolo/local_node_bridge.py
kolo/mark-and-text-black.png
kolo/mcp_plumbing.py
kolo/mcp_server.py
kolo/middleware.py
kolo/monitoring.py
kolo/open_in_pycharm.py
kolo/plugins.py
kolo/profiler.py
kolo/pytest_plugin.py
kolo/serialize.py
kolo/settings.py
kolo/sql_overview.py
kolo/threads.py
kolo/types.py
kolo/upload.py
kolo/utils.py
kolo/version.py
kolo/web/__init__.py
kolo/web/api.py
kolo/web/django.py
kolo/web/home.py
kolo/web/server.py
kolo/web/static/.gitignore
kolo/web/static/favicons/favicon-dark-16x16.png
kolo/web/static/favicons/favicon-dark-32x32.png
kolo/web/static/favicons/favicon-light-16x16.png
kolo/web/static/favicons/favicon-light-32x32.png
kolo/web/static/favicons/favicon.ico
kolo/web/static/spa/main.css
kolo/web/static/spa/main.css.map
kolo/web/static/spa/main.js
kolo/web/static/spa/main.js.LICENSE.txt
kolo/web/static/spa/main.js.map
kolo/web/templates/home.html
kolo-2.40.1.dist-info/RECORD
